binderhub/__init__.py
binderhub/__main__.py
binderhub/_version.py
binderhub/app.py
binderhub/base.py
binderhub/build.py
binderhub/builder.py
binderhub/events.py
binderhub/launcher.py
binderhub/main.py
binderhub/metrics.py
binderhub/registry.py
binderhub/repoproviders.py
binderhub/utils.py
binderhub/static/favicon.ico
binderhub/static/index.css
binderhub/static/loading.css
binderhub/static/logo.svg
binderhub/static/dist/448c34a56d699c29117adc64c43affeb.woff2
binderhub/static/dist/4cf6f681b05ddc6375e51c804a496fe2.woff
binderhub/static/dist/89889688147bd7575d6327160d64e760.svg
binderhub/static/dist/a493884b8da5e40a49761e45e26632b7.woff
binderhub/static/dist/bundle.js
binderhub/static/dist/bundle.js.map
binderhub/static/dist/cc10b51ebde2156baf4012fbc9b3a0c1.woff
binderhub/static/dist/e18bbf611f2a2e43afc071aa2f4e1512.ttf
binderhub/static/dist/f4769f9bdb7466be65088239c12046d1.eot
binderhub/static/dist/fa2772327f55d8198301fdb8bcfc8158.woff
binderhub/static/dist/styles.css
binderhub/static/dist/styles.css.map
binderhub/static/fonts/clearsans/LICENSE-2.0.txt
binderhub/static/fonts/clearsans/WOFF/ClearSans-Bold.woff
binderhub/static/fonts/clearsans/WOFF/ClearSans-BoldItalic.woff
binderhub/static/fonts/clearsans/WOFF/ClearSans-Italic.woff
binderhub/static/fonts/clearsans/WOFF/ClearSans-Light.woff
binderhub/static/fonts/clearsans/WOFF/ClearSans-Medium.woff
binderhub/static/fonts/clearsans/WOFF/ClearSans-MediumItalic.woff
binderhub/static/fonts/clearsans/WOFF/ClearSans-Regular.woff
binderhub/static/fonts/clearsans/WOFF/ClearSans-Thin.woff
binderhub/static/images/badge.svg
binderhub/static/images/caretdown-white.svg
binderhub/static/images/clipboard.svg
binderhub/static/images/copy-icon-black.svg
binderhub/static/images/copy-icon-white.svg
binderhub/static/images/favicon_building.ico
binderhub/static/images/favicon_fail.ico
binderhub/static/images/favicon_success.ico
binderhub/static/images/markdown-icon.svg
binderhub-0.1.0.dist-info/METADATA
binderhub-0.1.0.dist-info/RECORD
binderhub-0.1.0.dist-info/WHEEL
binderhub-0.1.0.dist-info/top_level.txt
