Metadata-Version: 2.1
Name: binderhub
Version: 0.1.0
Summary: Turn a Git repo into a collection of interactive notebooks
Home-page: https://binderhub.readthedocs.io/en/latest/
Author: Project Jupyter Contributors
Author-email: jupyter@googlegroups.com
License: BSD
Project-URL: Documentation, https://binderhub.readthedocs.io/en/latest/
Project-URL: Funding, https://jupyter.org/about
Project-URL: Source, https://github.com/jupyterhub/binderhub/
Project-URL: Tracker, https://github.com/jupyterhub/binderhub/issues
Keywords: reproducible science environments docker kubernetes
Platform: UNKNOWN
Requires-Python: >=3.6
Requires-Dist: kubernetes (>=4.*)
Requires-Dist: escapism
Requires-Dist: tornado
Requires-Dist: traitlets
Requires-Dist: docker
Requires-Dist: jinja2
Requires-Dist: prometheus-client
Requires-Dist: python-json-logger
Requires-Dist: jupyterhub
